django_semantic_search/__init__.py
django_semantic_search/apps.py
django_semantic_search/backends/__init__.py
django_semantic_search/backends/base.py
django_semantic_search/backends/qdrant.py
django_semantic_search/backends/types.py
django_semantic_search/decorators.py
django_semantic_search/default_settings.py
django_semantic_search/documents.py
django_semantic_search/embeddings/__init__.py
django_semantic_search/embeddings/base.py
django_semantic_search/embeddings/fastembed.py
django_semantic_search/embeddings/openai.py
django_semantic_search/embeddings/sentence_transformers.py
django_semantic_search/types.py
django_semantic_search/utils.py
django_semantic_search-0.2.1.dist-info/LICENSE
django_semantic_search-0.2.1.dist-info/METADATA
django_semantic_search-0.2.1.dist-info/WHEEL
django_semantic_search-0.2.1.dist-info/RECORD
