Metadata-Version: 2.3
Name: django-semantic-search
Version: 0.2.1
Summary: Bringing semantic search to Django. Integrates seamlessly with Django ORM.
License: Apache-2.0
Author: Kacper Łukawski
Author-email: lukawski.kacper@gmail.com
Requires-Python: >=3.10
Classifier: License :: OSI Approved :: Apache Software License
Classifier: Programming Language :: Python :: 3
Classifier: Programming Language :: Python :: 3.10
Classifier: Programming Language :: Python :: 3.11
Classifier: Programming Language :: Python :: 3.12
Classifier: Programming Language :: Python :: 3.13
Provides-Extra: all
Provides-Extra: fastembed
Provides-Extra: openai
Provides-Extra: qdrant
Provides-Extra: sentence-transformers
Requires-Dist: django (>=5.0)
Requires-Dist: fastembed (>=0.6.1,<0.7.0) ; extra == "fastembed" or extra == "all"
Requires-Dist: openai (>=1.0.0,<2.0.0) ; extra == "openai" or extra == "all"
Requires-Dist: qdrant-client (>=1.11.1,<2.0.0) ; extra == "qdrant" or extra == "all"
Requires-Dist: sentence-transformers (>=4.1.0,<5.0.0) ; extra == "sentence-transformers" or extra == "all"
Requires-Dist: torch (>=2.0.0,<3.0.0) ; (sys_platform != "darwin") and (extra == "sentence-transformers" or extra == "all")
Requires-Dist: torch (>=2.0.0,<3.0.0) ; (sys_platform == "darwin") and (extra == "sentence-transformers" or extra == "all")
